{"chords": [{"index": 0, "degree-triad": "I:maj", "degree-full": "I:maj", "name-triad": "E:maj", "name-full": "E:maj", "popular-style": "E"}, {"index": 1, "degree-triad": "I:maj", "degree-full": "I:maj6", "name-triad": "E:maj", "name-full": "E:maj6", "popular-style": "E6"}, {"index": 2, "degree-triad": "V:min", "degree-full": "V:min7/11", "name-triad": "B:min", "name-full": "B:min7/11", "popular-style": "Bm"}, {"index": 3, "degree-triad": "I:maj", "degree-full": "I:maj", "name-triad": "E:maj", "name-full": "E:maj", "popular-style": "E"}, {"index": 4, "degree-triad": "I:maj", "degree-full": "I:maj", "name-triad": "E:maj", "name-full": "E:maj", "popular-style": "E"}, {"index": 5, "degree-triad": "I:maj", "degree-full": "I:maj6", "name-triad": "E:maj", "name-full": "E:maj6", "popular-style": "E6"}, {"index": 6, "degree-triad": "V:min", "degree-full": "V:min7/11", "name-triad": "B:min", "name-full": "B:min7/11", "popular-style": "Bm"}, {"index": 7, "degree-triad": "I:maj", "degree-full": "I:maj", "name-triad": "E:maj", "name-full": "E:maj", "popular-style": "E"}, {"index": 8, "degree-triad": "I:maj", "degree-full": "I:maj", "name-triad": "E:maj", "name-full": "E:maj", "popular-style": "E"}, {"index": 9, "degree-triad": "V:maj", "degree-full": "V:maj", "name-triad": "B:maj", "name-full": "B:maj", "popular-style": "B"}, {"index": 10, "degree-triad": "IV:maj", "degree-full": "IV:maj", "name-triad": "A:maj", "name-full": "A:maj", "popular-style": "A"}, {"index": 11, "degree-triad": "VI:min", "degree-full": "VI:min7", "name-triad": "C#:min", "name-full": "C#:min7", "popular-style": "C#m7"}, {"index": 12, "degree-triad": "VI:maj", "degree-full": "VI:sus2(b7)", "name-triad": "C#:maj", "name-full": "C#:sus2(b7)", "popular-style": "C#"}, {"index": 13, "degree-triad": "I:maj", "degree-full": "I:maj", "name-triad": "E:maj", "name-full": "E:maj", "popular-style": "E"}, {"index": 14, "degree-triad": "V:maj", "degree-full": "V:maj", "name-triad": "B:maj", "name-full": "B:maj", "popular-style": "B"}, {"index": 15, "degree-triad": "IV:maj", "degree-full": "IV:maj", "name-triad": "A:maj", "name-full": "A:maj", "popular-style": "A"}, {"index": 16, "degree-triad": "VI:min", "degree-full": "VI:min7", "name-triad": "C#:min", "name-full": "C#:min7", "popular-style": "C#m7"}, {"index": 17, "degree-triad": "IV:maj", "degree-full": "IV:maj6", "name-triad": "A:maj", "name-full": "A:maj6", "popular-style": "A6"}, {"index": 18, "degree-triad": "I:maj", "degree-full": "I:maj", "name-triad": "E:maj", "name-full": "E:maj", "popular-style": "E"}, {"index": 19, "degree-triad": "V:maj", "degree-full": "V:maj", "name-triad": "B:maj", "name-full": "B:maj", "popular-style": "B"}, {"index": 20, "degree-triad": "IV:maj", "degree-full": "IV:maj", "name-triad": "A:maj", "name-full": "A:maj", "popular-style": "A"}, {"index": 21, "degree-triad": "VI:min", "degree-full": "VI:min7", "name-triad": "C#:min", "name-full": "C#:min7", "popular-style": "C#m7"}, {"index": 22, "degree-triad": "IV:maj", "degree-full": "IV:maj6", "name-triad": "A:maj", "name-full": "A:maj6", "popular-style": "A6"}, {"index": 23, "degree-triad": "I:maj", "degree-full": "I:maj", "name-triad": "E:maj", "name-full": "E:maj", "popular-style": "E"}, {"index": 24, "degree-triad": "V:maj", "degree-full": "V:maj", "name-triad": "B:maj", "name-full": "B:maj", "popular-style": "B"}, {"index": 25, "degree-triad": "IV:maj", "degree-full": "IV:maj", "name-triad": "A:maj", "name-full": "A:maj", "popular-style": "A"}, {"index": 26, "degree-triad": "VI:min", "degree-full": "VI:min7", "name-triad": "C#:min", "name-full": "C#:min7", "popular-style": "C#m7"}, {"index": 27, "degree-triad": "IV:maj", "degree-full": "IV:maj7", "name-triad": "A:maj", "name-full": "A:maj7", "popular-style": "AM7"}, {"index": 28, "degree-triad": "I:maj", "degree-full": "I:maj", "name-triad": "E:maj", "name-full": "E:maj", "popular-style": "E"}, {"index": 29, "degree-triad": "I:maj", "degree-full": "I:maj6", "name-triad": "E:maj", "name-full": "E:maj6", "popular-style": "E6"}, {"index": 30, "degree-triad": "V:min", "degree-full": "V:min7/11", "name-triad": "B:min", "name-full": "B:min7/11", "popular-style": "Bm"}, {"index": 31, "degree-triad": "I:maj", "degree-full": "I:maj", "name-triad": "E:maj", "name-full": "E:maj", "popular-style": "E"}, {"index": 32, "degree-triad": "I:maj", "degree-full": "I:maj", "name-triad": "E:maj", "name-full": "E:maj", "popular-style": "E"}, {"index": 33, "degree-triad": "I:maj", "degree-full": "I:maj6", "name-triad": "E:maj", "name-full": "E:maj6", "popular-style": "E6"}, {"index": 34, "degree-triad": "V:min", "degree-full": "V:min7/11", "name-triad": "B:min", "name-full": "B:min7/11", "popular-style": "Bm"}, {"index": 35, "degree-triad": "I:maj", "degree-full": "I:maj", "name-triad": "E:maj", "name-full": "E:maj", "popular-style": "E"}, {"index": 36, "degree-triad": "I:maj", "degree-full": "I:maj", "name-triad": "E:maj", "name-full": "E:maj", "popular-style": "E"}, {"index": 37, "degree-triad": "V:maj", "degree-full": "V:maj", "name-triad": "B:maj", "name-full": "B:maj", "popular-style": "B"}, {"index": 38, "degree-triad": "IV:maj", "degree-full": "IV:maj", "name-triad": "A:maj", "name-full": "A:maj", "popular-style": "A"}, {"index": 39, "degree-triad": "VI:min", "degree-full": "VI:min7", "name-triad": "C#:min", "name-full": "C#:min7", "popular-style": "C#m7"}, {"index": 40, "degree-triad": "VI:maj", "degree-full": "VI:sus2(b7)", "name-triad": "C#:maj", "name-full": "C#:sus2(b7)", "popular-style": "C#"}, {"index": 41, "degree-triad": "I:maj", "degree-full": "I:maj", "name-triad": "E:maj", "name-full": "E:maj", "popular-style": "E"}, {"index": 42, "degree-triad": "V:maj", "degree-full": "V:maj", "name-triad": "B:maj", "name-full": "B:maj", "popular-style": "B"}, {"index": 43, "degree-triad": "IV:maj", "degree-full": "IV:maj", "name-triad": "A:maj", "name-full": "A:maj", "popular-style": "A"}, {"index": 44, "degree-triad": "VI:min", "degree-full": "VI:min7", "name-triad": "C#:min", "name-full": "C#:min7", "popular-style": "C#m7"}, {"index": 45, "degree-triad": "IV:maj", "degree-full": "IV:maj6", "name-triad": "A:maj", "name-full": "A:maj6", "popular-style": "A6"}, {"index": 46, "degree-triad": "I:maj", "degree-full": "I:maj", "name-triad": "E:maj", "name-full": "E:maj", "popular-style": "E"}, {"index": 47, "degree-triad": "V:maj", "degree-full": "V:maj", "name-triad": "B:maj", "name-full": "B:maj", "popular-style": "B"}, {"index": 48, "degree-triad": "IV:maj", "degree-full": "IV:maj", "name-triad": "A:maj", "name-full": "A:maj", "popular-style": "A"}, {"index": 49, "degree-triad": "VI:min", "degree-full": "VI:min7", "name-triad": "C#:min", "name-full": "C#:min7", "popular-style": "C#m7"}, {"index": 50, "degree-triad": "V:maj", "degree-full": "V:7", "name-triad": "B:maj", "name-full": "B:7", "popular-style": "B7"}, {"index": 51, "degree-triad": "I:maj", "degree-full": "I:maj", "name-triad": "E:maj", "name-full": "E:maj", "popular-style": "E"}, {"index": 52, "degree-triad": "V:maj", "degree-full": "V:maj", "name-triad": "B:maj", "name-full": "B:maj", "popular-style": "B"}, {"index": 53, "degree-triad": "IV:maj", "degree-full": "IV:maj", "name-triad": "A:maj", "name-full": "A:maj", "popular-style": "A"}, {"index": 54, "degree-triad": "VI:min", "degree-full": "VI:min7", "name-triad": "C#:min", "name-full": "C#:min7", "popular-style": "C#m7"}, {"index": 55, "degree-triad": "IV:maj", "degree-full": "IV:maj7", "name-triad": "A:maj", "name-full": "A:maj7", "popular-style": "AM7"}, {"index": 56, "degree-triad": "I:maj", "degree-full": "I:maj", "name-triad": "E:maj", "name-full": "E:maj", "popular-style": "E"}, {"index": 57, "degree-triad": "I:maj", "degree-full": "I:maj6", "name-triad": "E:maj", "name-full": "E:maj6", "popular-style": "E6"}, {"index": 58, "degree-triad": "V:min", "degree-full": "V:min7/11", "name-triad": "B:min", "name-full": "B:min7/11", "popular-style": "Bm"}, {"index": 59, "degree-triad": "I:maj", "degree-full": "I:maj", "name-triad": "E:maj", "name-full": "E:maj", "popular-style": "E"}, {"index": 60, "degree-triad": "I:maj", "degree-full": "I:maj", "name-triad": "E:maj", "name-full": "E:maj", "popular-style": "E"}, {"index": 61, "degree-triad": "I:maj", "degree-full": "I:maj6", "name-triad": "E:maj", "name-full": "E:maj6", "popular-style": "E6"}, {"index": 62, "degree-triad": "V:min", "degree-full": "V:min7/11", "name-triad": "B:min", "name-full": "B:min7/11", "popular-style": "Bm"}, {"index": 63, "degree-triad": "I:maj", "degree-full": "I:maj", "name-triad": "E:maj", "name-full": "E:maj", "popular-style": "E"}, {"index": 64, "degree-triad": "I:maj", "degree-full": "I:maj", "name-triad": "E:maj", "name-full": "E:maj", "popular-style": "E"}, {"index": 65, "degree-triad": "V:maj", "degree-full": "V:maj", "name-triad": "B:maj", "name-full": "B:maj", "popular-style": "B"}, {"index": 66, "degree-triad": "IV:maj", "degree-full": "IV:maj", "name-triad": "A:maj", "name-full": "A:maj", "popular-style": "A"}, {"index": 67, "degree-triad": "VI:min", "degree-full": "VI:min7", "name-triad": "C#:min", "name-full": "C#:min7", "popular-style": "C#m7"}, {"index": 68, "degree-triad": "VI:maj", "degree-full": "VI:sus2(b7)", "name-triad": "C#:maj", "name-full": "C#:sus2(b7)", "popular-style": "C#"}, {"index": 69, "degree-triad": "I:maj", "degree-full": "I:maj", "name-triad": "E:maj", "name-full": "E:maj", "popular-style": "E"}, {"index": 70, "degree-triad": "V:maj", "degree-full": "V:maj", "name-triad": "B:maj", "name-full": "B:maj", "popular-style": "B"}, {"index": 71, "degree-triad": "IV:maj", "degree-full": "IV:maj", "name-triad": "A:maj", "name-full": "A:maj", "popular-style": "A"}, {"index": 72, "degree-triad": "VI:min", "degree-full": "VI:min7", "name-triad": "C#:min", "name-full": "C#:min7", "popular-style": "C#m7"}, {"index": 73, "degree-triad": "IV:maj", "degree-full": "IV:maj6(9)", "name-triad": "A:maj", "name-full": "A:maj6(9)", "popular-style": "A"}, {"index": 74, "degree-triad": "I:maj", "degree-full": "I:maj", "name-triad": "E:maj", "name-full": "E:maj", "popular-style": "E"}, {"index": 75, "degree-triad": "V:maj", "degree-full": "V:maj", "name-triad": "B:maj", "name-full": "B:maj", "popular-style": "B"}, {"index": 76, "degree-triad": "IV:maj", "degree-full": "IV:maj", "name-triad": "A:maj", "name-full": "A:maj", "popular-style": "A"}, {"index": 77, "degree-triad": "VI:min", "degree-full": "VI:min7", "name-triad": "C#:min", "name-full": "C#:min7", "popular-style": "C#m7"}, {"index": 78, "degree-triad": "IV:maj", "degree-full": "IV:maj", "name-triad": "A:maj", "name-full": "A:maj", "popular-style": "A"}, {"index": 79, "degree-triad": "I:maj", "degree-full": "I:maj", "name-triad": "E:maj", "name-full": "E:maj", "popular-style": "E"}, {"index": 80, "degree-triad": "V:maj", "degree-full": "V:maj", "name-triad": "B:maj", "name-full": "B:maj", "popular-style": "B"}, {"index": 81, "degree-triad": "IV:maj", "degree-full": "IV:maj", "name-triad": "A:maj", "name-full": "A:maj", "popular-style": "A"}, {"index": 82, "degree-triad": "VI:min", "degree-full": "VI:min7", "name-triad": "C#:min", "name-full": "C#:min7", "popular-style": "C#m7"}, {"index": 83, "degree-triad": "IV:maj", "degree-full": "IV:maj7", "name-triad": "A:maj", "name-full": "A:maj7", "popular-style": "AM7"}, {"index": 84, "degree-triad": "I:maj", "degree-full": "I:maj", "name-triad": "E:maj", "name-full": "E:maj", "popular-style": "E"}, {"index": 85, "degree-triad": "I:maj", "degree-full": "I:maj6", "name-triad": "E:maj", "name-full": "E:maj6", "popular-style": "E6"}, {"index": 86, "degree-triad": "V:min", "degree-full": "V:min7/11", "name-triad": "B:min", "name-full": "B:min7/11", "popular-style": "Bm"}, {"index": 87, "degree-triad": "I:maj", "degree-full": "I:maj", "name-triad": "E:maj", "name-full": "E:maj", "popular-style": "E"}, {"index": 88, "degree-triad": "I:maj", "degree-full": "I:maj", "name-triad": "E:maj", "name-full": "E:maj", "popular-style": "E"}, {"index": 89, "degree-triad": "I:maj", "degree-full": "I:maj6", "name-triad": "E:maj", "name-full": "E:maj6", "popular-style": "E6"}, {"index": 90, "degree-triad": "V:min", "degree-full": "V:min7/11", "name-triad": "B:min", "name-full": "B:min7/11", "popular-style": "Bm"}, {"index": 91, "degree-triad": "IV:maj", "degree-full": "IV:maj6(9)", "name-triad": "A:maj", "name-full": "A:maj6(9)", "popular-style": "A"}, {"index": 92, "degree-triad": "V:min", "degree-full": "V:min7/11", "name-triad": "B:min", "name-full": "B:min7/11", "popular-style": "Bm"}, {"index": 93, "degree-triad": "IV:maj", "degree-full": "IV:maj6(9)", "name-triad": "A:maj", "name-full": "A:maj6(9)", "popular-style": "A"}, {"index": 94, "degree-triad": "V:min", "degree-full": "V:min7/11", "name-triad": "B:min", "name-full": "B:min7/11", "popular-style": "Bm"}, {"index": 95, "degree-triad": "IV:maj", "degree-full": "IV:maj6(9)", "name-triad": "A:maj", "name-full": "A:maj6(9)", "popular-style": "A"}, {"index": 96, "degree-triad": "I:maj", "degree-full": "I:maj", "name-triad": "E:maj", "name-full": "E:maj", "popular-style": "E"}], "chorusSegments": [{"index": 0, "repeats": [{"length": 7, "id": 28}, {"length": 7, "id": 56}]}], "song": {"tonic": "E", "artist": "David Crosby,Graham Nash", "id": 1124, "title": "Carry Me"}}